ddniux_obs/__init__.py
ddniux_obs/obs_manager.py
ddniux_obs-0.1.1.dist-info/LICENSE
ddniux_obs-0.1.1.dist-info/METADATA
ddniux_obs-0.1.1.dist-info/WHEEL
ddniux_obs-0.1.1.dist-info/top_level.txt
ddniux_obs-0.1.1.dist-info/RECORD
