Metadata-Version: 2.1
Name: ddniux_obs
Version: 0.1.1
Summary: HUAWEI OBS SDK
Home-page: https://github.com/yourusername/your-package-name
Author: Fletcher Zang
Author-email: 925637800@qq.com
Classifier: Programming Language :: Python :: 3
Classifier: License :: OSI Approved :: MIT License
Classifier: Operating System :: OS Independent
Requires-Python: >=3.6
License-File: LICENSE
